autogenlib/__init__.py
autogenlib/_cache.py
autogenlib/_caller.py
autogenlib/_context.py
autogenlib/_exception_handler.py
autogenlib/_finder.py
autogenlib/_generator.py
autogenlib/_state.py
autogenlib-0.1.3.dist-info/METADATA
autogenlib-0.1.3.dist-info/WHEEL
autogenlib-0.1.3.dist-info/licenses/LICENSE
autogenlib-0.1.3.dist-info/RECORD
