Metadata-Version: 2.4
Name: autogenlib
Version: 0.1.3
Summary: Import wisdom, export code.
Project-URL: Homepage, https://github.com/cofob/autogenlib
Author-email: Egor Ternovoi <i.am@cfb.wtf>
License-File: LICENSE
Classifier: License :: OSI Approved :: MIT License
Classifier: Operating System :: OS Independent
Classifier: Programming Language :: Python :: 3
Requires-Python: >=3.12
Requires-Dist: openai>=1.78.0
